sfbulk2.py
sfbulk2-0.8.0.dist-info/LICENSE.txt
sfbulk2-0.8.0.dist-info/METADATA
sfbulk2-0.8.0.dist-info/WHEEL
sfbulk2-0.8.0.dist-info/top_level.txt
sfbulk2-0.8.0.dist-info/RECORD
